Assignment2/saxl_lfsr.v
module s_axil #(
    parameter C_AXIL_ADDR_WIDTH = 4,
    parameter C_AXIL_DATA_WIDTH = 32
)(
    input aclk,
    input aresetn,

    // AXI-Lite Slave Interface
    input  [C_AXIL_ADDR_WIDTH-1:0] s_axi_awaddr,
    input                       s_axi_awvalid,
    output reg                  s_axi_awready,

    input  [C_AXIL_DATA_WIDTH-1:0] s_axi_wdata,
    input                       s_axi_wvalid,
    output reg                  s_axi_wready,

    output reg [1:0]            s_axi_bresp,
    output reg                  s_axi_bvalid,
    input                       s_axi_bready,

    input  [C_AXIL_ADDR_WIDTH-1:0] s_axi_araddr,
    input                       s_axi_arvalid,
    output reg                  s_axi_arready,

    output reg [C_AXIL_DATA_WIDTH-1:0] s_axi_rdata,
    output reg [1:0]            s_axi_rresp,
    output reg                  s_axi_rvalid,
    input                       s_axi_rready,

    // AXI - Stream Master Interface
    output reg [C_AXIL_DATA_WIDTH-1:0] m_axis_tdata,
    output reg                    m_axis_tvalid,
    input                         m_axis_tready
);

    // Address map for these registers
    // 0x00 - start_reg
    // 0x04 - stop_reg
    // 0x08 - seed_reg
    // 0x0C - taps_reg

    // Registers
    reg start_reg;
    reg stop_reg;
    reg [7:0] seed_reg;
    reg [7:0] taps_reg;
    
    // LFSR registers
    reg [7:0] lfsr_reg;
    reg lfsr_valid;
    wire feedback;
    
    // AXI-Lite write address channel
    reg write_enable;
    reg [C_AXIL_ADDR_WIDTH-1:0] write_addr;
    
    // AXI-Lite read address channel
    reg read_enable;
    reg [C_AXIL_ADDR_WIDTH-1:0] read_addr;
    
    // LFSR ready for next transfer
    wire lfsr_ready;
    assign lfsr_ready = m_axis_tready || !m_axis_tvalid;
    
    // AXI-Lite write address channel logic
    always @(posedge aclk) begin
        if (!aresetn) begin
            s_axi_awready <= 1'b0;
            write_enable <= 1'b0;
            write_addr <= {C_AXIL_ADDR_WIDTH{1'b0}};
        end else begin
            if (s_axi_awvalid && !s_axi_awready && s_axi_wvalid && !write_enable) begin
                s_axi_awready <= 1'b1;
                write_addr <= s_axi_awaddr;
                write_enable <= 1'b1;
            end else begin
                s_axi_awready <= 1'b0;
                if (s_axi_bready && s_axi_bvalid) begin
                    write_enable <= 1'b0;
                end
            end
        end
    end
    
    // AXI-Lite write data channel logic
    always @(posedge aclk) begin
        if (!aresetn) begin
            s_axi_wready <= 1'b0;
            s_axi_bvalid <= 1'b0;
            s_axi_bresp <= 2'b00;
            start_reg <= 1'b0;
            stop_reg <= 1'b0;
            seed_reg <= 8'h01;  // Default non-zero seed
            taps_reg <= 8'hB8;  // Default taps (x^8 + x^6 + x^5 + x^4 + 1)
        end else begin
            if (s_axi_wvalid && !s_axi_wready && write_enable) begin
                s_axi_wready <= 1'b1;
                
                // Register writes based on address
                case (write_addr)
                    4'h0: start_reg <= s_axi_wdata[0];
                    4'h4: stop_reg <= s_axi_wdata[0];
                    4'h8: seed_reg <= s_axi_wdata[7:0];
                    4'hC: taps_reg <= s_axi_wdata[7:0];
                    default: begin end
                endcase
                
                // Write response
                s_axi_bresp <= 2'b00;  // OKAY response
                s_axi_bvalid <= 1'b1;
            end else begin
                s_axi_wready <= 1'b0;
                if (s_axi_bready && s_axi_bvalid) begin
                    s_axi_bvalid <= 1'b0;
                end
            end
        end
    end
    
    // AXI-Lite read address channel logic
    always @(posedge aclk) begin
        if (!aresetn) begin
            s_axi_arready <= 1'b0;
            read_enable <= 1'b0;
            read_addr <= {C_AXIL_ADDR_WIDTH{1'b0}};
        end else begin
            if (s_axi_arvalid && !s_axi_arready && !read_enable) begin
                s_axi_arready <= 1'b1;
                read_addr <= s_axi_araddr;
                read_enable <= 1'b1;
            end else begin
                s_axi_arready <= 1'b0;
                if (s_axi_rready && s_axi_rvalid) begin
                    read_enable <= 1'b0;
                end
            end
        end
    end
    
    // AXI-Lite read data channel logic
    always @(posedge aclk) begin
        if (!aresetn) begin
            s_axi_rvalid <= 1'b0;
            s_axi_rdata <= {C_AXIL_DATA_WIDTH{1'b0}};
            s_axi_rresp <= 2'b00;
        end else begin
            if (read_enable && !s_axi_rvalid) begin
                s_axi_rvalid <= 1'b1;
                s_axi_rresp <= 2'b00;  // OKAY response
                
                // Register reads based on address
                case (read_addr)
                    4'h0: s_axi_rdata <= {{C_AXIL_DATA_WIDTH-1{1'b0}}, start_reg};
                    4'h4: s_axi_rdata <= {{C_AXIL_DATA_WIDTH-1{1'b0}}, stop_reg};
                    4'h8: s_axi_rdata <= {{C_AXIL_DATA_WIDTH-8{1'b0}}, seed_reg};
                    4'hC: s_axi_rdata <= {{C_AXIL_DATA_WIDTH-8{1'b0}}, taps_reg};
                    default: s_axi_rdata <= {C_AXIL_DATA_WIDTH{1'b0}};
                endcase
            end else begin
                if (s_axi_rready && s_axi_rvalid) begin
                    s_axi_rvalid <= 1'b0;
                end
            end
        end
    end
    
    // LFSR feedback calculation
    // XOR the bits selected by the taps_reg
    assign feedback = ^(lfsr_reg & taps_reg);
    
    // LFSR operation
    always @(posedge aclk) begin
        if (!aresetn) begin
            lfsr_reg <= 8'h01;  // Default non-zero value
            lfsr_valid <= 1'b0;
            m_axis_tvalid <= 1'b0;
            m_axis_tdata <= {C_AXIL_DATA_WIDTH{1'b0}};
        end else begin
            if (start_reg && !stop_reg && lfsr_ready) begin
                // Load seed if LFSR is in reset state (all zeros)
                if (lfsr_reg == 8'h00) begin
                    lfsr_reg <= seed_reg;
                end else begin
                    // Normal LFSR operation
                    lfsr_reg <= {lfsr_reg[6:0], feedback};
                end
                
                // Set valid flag for new data
                lfsr_valid <= 1'b1;
            end
            
            // Handle seed loading when start is first asserted
            if (start_reg && !lfsr_valid) begin
                lfsr_reg <= seed_reg;
                lfsr_valid <= 1'b1;
            end
            
            // Reset operation
            if (stop_reg) begin
                lfsr_valid <= 1'b0;
            end
            
            // AXI-Stream master output
            if (lfsr_valid && lfsr_ready) begin
                m_axis_tvalid <= 1'b1;
                // Output the 8-bit LFSR value zero-padded to 32-bits
                m_axis_tdata <= {{(C_AXIL_DATA_WIDTH-8){1'b0}}, lfsr_reg};
            end else if (m_axis_tready && m_axis_tvalid) begin
                m_axis_tvalid <= 1'b0;
            end
        end
    end

endmodule

Assignment2/q1_tb.v
`timescale 1ns/1ps
`include "saxl_lfsr.v"
module tb_s_axil_basic();

    parameter CLK_PERIOD = 10;  // 100 MHz clock
    parameter SIM_DURATION = 1000; // 1us total simulation
    parameter TIMEOUT = 100; // Timeout for AXI transactions

    reg aclk;
    reg aresetn;
    
    // AXI-Lite Interface
    reg [3:0] s_axi_awaddr;
    reg s_axi_awvalid;
    wire s_axi_awready;
    
    reg [31:0] s_axi_wdata;
    reg s_axi_wvalid;
    wire s_axi_wready;
    
    wire [1:0] s_axi_bresp;
    wire s_axi_bvalid;
    reg s_axi_bready;
    
    // AXI-Stream Interface
    wire [31:0] m_axis_tdata;
    wire m_axis_tvalid;
    reg m_axis_tready;

    // Instantiate DUT
    s_axil dut (
        .aclk(aclk),
        .aresetn(aresetn),
        .s_axi_awaddr(s_axi_awaddr),
        .s_axi_awvalid(s_axi_awvalid),
        .s_axi_awready(s_axi_awready),
        .s_axi_wdata(s_axi_wdata),
        .s_axi_wvalid(s_axi_wvalid),
        .s_axi_wready(s_axi_wready),
        .s_axi_bresp(s_axi_bresp),
        .s_axi_bvalid(s_axi_bvalid),
        .s_axi_bready(s_axi_bready),
        .s_axi_araddr(4'b0),
        .s_axi_arvalid(1'b0),
        .s_axi_arready(),
        .s_axi_rdata(),
        .s_axi_rresp(),
        .s_axi_rvalid(),
        .s_axi_rready(1'b0),
        .m_axis_tdata(m_axis_tdata),
        .m_axis_tvalid(m_axis_tvalid),
        .m_axis_tready(m_axis_tready)
    );

    // Generate VCD file
    initial begin
        $dumpfile("lfsr_wave.vcd");
        $dumpvars(0, tb_s_axil_basic);
    end

    // Clock generation
    initial begin
        aclk = 0;
        forever #(CLK_PERIOD/2) aclk = ~aclk;
    end

    // Simulation timeout
    initial begin
        #SIM_DURATION;
        $display("Simulation finished");
        $finish;
    end

    // Main test sequence
    reg test_failed;
    initial begin
        test_failed = 0;
        
        // Initialize
        aresetn = 0;
        s_axi_awaddr = 0;
        s_axi_awvalid = 0;
        s_axi_wdata = 0;
        s_axi_wvalid = 0;
        s_axi_bready = 1;
        m_axis_tready = 1;
        
        // Reset
        #100;
        aresetn = 1;
        #100;
        
        // Test sequence
        $display("Starting test sequence");
        
        // 1. Set seed
        axi_write(4'h8, 32'h000000A5);
        if (test_failed) begin
            $display("Error: Failed to set seed");
            $finish;
        end
        
        // 2. Start LFSR
        axi_write(4'h0, 32'h00000001);
        if (test_failed) begin
            $display("Error: Failed to start LFSR");
            $finish;
        end
        
        // 3. Let it run
        #500;
        
        // 4. Stop LFSR
        axi_write(4'h4, 32'h00000001);
        if (test_failed) begin
            $display("Error: Failed to stop LFSR");
            $finish;
        end
        
        #100;
        $display("Test completed successfully");
        $finish;
    end

    // AXI-Lite write task with timeout (Verilog style)
    task axi_write;
        input [3:0] addr;
        input [31:0] data;
        integer timeout;
        begin
            test_failed = 0;
            timeout = 0;
            
            @(posedge aclk);
            s_axi_awaddr = addr;
            s_axi_awvalid = 1;
            s_axi_wdata = data;
            s_axi_wvalid = 1;
            
            while (!(s_axi_awready && s_axi_wready) && timeout < TIMEOUT) begin
                @(posedge aclk);
                timeout = timeout + 1;
            end
            
            if (timeout >= TIMEOUT) begin
                $display("Timeout waiting for write ready");
                s_axi_awvalid = 0;
                s_axi_wvalid = 0;
                test_failed = 1;
                disable axi_write;
            end
            
            @(posedge aclk);
            s_axi_awvalid = 0;
            s_axi_wvalid = 0;
            
            timeout = 0;
            while (!s_axi_bvalid && timeout < TIMEOUT) begin
                @(posedge aclk);
                timeout = timeout + 1;
            end
            
            if (timeout >= TIMEOUT) begin
                $display("Timeout waiting for write response");
                test_failed = 1;
                disable axi_write;
            end
            
            if (s_axi_bresp !== 2'b00) begin
                $display("Write error response: %b", s_axi_bresp);
                test_failed = 1;
                disable axi_write;
            end
            
            @(posedge aclk);
        end
    endtask

    // Monitor LFSR output
    always @(posedge aclk) begin
        if (m_axis_tvalid && m_axis_tready) begin
            $display("LFSR output: 0x%h", m_axis_tdata[7:0]);
        end
    end

endmodule

Assignment2/lfsr_wave.vcd
$date
	Fri Apr 04 00:04:42 2025
$end
$version
	Icarus Verilog
$end
$timescale
	1ps
$end
$scope module tb_s_axil_basic $end
$var wire 1 ! s_axi_wready $end
$var wire 1 " s_axi_bvalid $end
$var wire 2 # s_axi_bresp [1:0] $end
$var wire 1 $ s_axi_awready $end
$var wire 1 % m_axis_tvalid $end
$var wire 32 & m_axis_tdata [31:0] $end
$var parameter 32 ' CLK_PERIOD $end
$var parameter 32 ( SIM_DURATION $end
$var parameter 32 ) TIMEOUT $end
$var reg 1 * aclk $end
$var reg 1 + aresetn $end
$var reg 1 , m_axis_tready $end
$var reg 4 - s_axi_awaddr [3:0] $end
$var reg 1 . s_axi_awvalid $end
$var reg 1 / s_axi_bready $end
$var reg 32 0 s_axi_wdata [31:0] $end
$var reg 1 1 s_axi_wvalid $end
$var reg 1 2 test_failed $end
$scope module dut $end
$var wire 1 * aclk $end
$var wire 1 + aresetn $end
$var wire 1 3 lfsr_ready $end
$var wire 1 , m_axis_tready $end
$var wire 4 4 s_axi_araddr [3:0] $end
$var wire 1 5 s_axi_arvalid $end
$var wire 4 6 s_axi_awaddr [3:0] $end
$var wire 1 . s_axi_awvalid $end
$var wire 1 / s_axi_bready $end
$var wire 1 7 s_axi_rready $end
$var wire 32 8 s_axi_wdata [31:0] $end
$var wire 1 1 s_axi_wvalid $end
$var wire 1 9 feedback $end
$var parameter 32 : C_AXIL_ADDR_WIDTH $end
$var parameter 32 ; C_AXIL_DATA_WIDTH $end
$var reg 8 < lfsr_reg [7:0] $end
$var reg 1 = lfsr_valid $end
$var reg 32 > m_axis_tdata [31:0] $end
$var reg 1 % m_axis_tvalid $end
$var reg 4 ? read_addr [3:0] $end
$var reg 1 @ read_enable $end
$var reg 1 A s_axi_arready $end
$var reg 1 $ s_axi_awready $end
$var reg 2 B s_axi_bresp [1:0] $end
$var reg 1 " s_axi_bvalid $end
$var reg 32 C s_axi_rdata [31:0] $end
$var reg 2 D s_axi_rresp [1:0] $end
$var reg 1 E s_axi_rvalid $end
$var reg 1 ! s_axi_wready $end
$var reg 8 F seed_reg [7:0] $end
$var reg 1 G start_reg $end
$var reg 1 H stop_reg $end
$var reg 8 I taps_reg [7:0] $end
$var reg 4 J write_addr [3:0] $end
$var reg 1 K write_enable $end
$upscope $end
$scope task axi_write $end
$var reg 4 L addr [3:0] $end
$var reg 32 M data [31:0] $end
$var integer 32 N timeout [31:0] $end
$upscope $end
$upscope $end
$enddefinitions $end
$comment Show the parameter values. $end
$dumpall
b100000 ;
b100 :
b1100100 )
b1111101000 (
b1010 '
$end
#0
$dumpvars
bx N
bx M
bx L
xK
bx J
bx I
xH
xG
bx F
xE
bx D
bx C
bx B
xA
x@
bx ?
bx >
x=
bx <
x9
b0 8
07
b0 6
05
b0 4
13
02
01
b0 0
1/
0.
b0 -
1,
0+
0*
bx &
x%
x$
bx #
x"
x!
$end
#5000
09
b0 J
0K
0$
b10111000 I
b1 F
0H
0G
b0 #
b0 B
0"
0!
b0 ?
0@
0A
b0 D
b0 C
0E
b0 &
b0 >
0%
0=
b1 <
1*
#10000
0*
#15000
1*
#20000
0*
#25000
1*
#30000
0*
#35000
1*
#40000
0*
#45000
1*
#50000
0*
#55000
1*
#60000
0*
#65000
1*
#70000
0*
#75000
1*
#80000
0*
#85000
1*
#90000
0*
#95000
1*
#100000
0*
1+
#105000
1*
#110000
0*
#115000
1*
#120000
0*
#125000
1*
#130000
0*
#135000
1*
#140000
0*
#145000
1*
#150000
0*
#155000
1*
#160000
0*
#165000
1*
#170000
0*
#175000
1*
#180000
0*
#185000
1*
#190000
0*
#195000
1*
#200000
0*
b0 N
b10100101 M
b1000 L
#205000
1K
b1000 J
1$
11
b10100101 0
b10100101 8
1.
b1000 -
b1000 6
1*
#210000
0*
#215000
1"
b10100101 F
1!
0$
b1 N
1*
#220000
0*
#225000
0K
0"
0!
b10 N
1*
#230000
0*
#235000
1K
1$
b11 N
1*
#240000
0*
#245000
0$
1"
1!
b100 N
1*
#250000
0*
#255000
0"
0!
0K
b101 N
1*
#260000
0*
#265000
1K
1$
b110 N
1*
#270000
0*
#275000
1"
1!
0$
b111 N
1*
#280000
0*
#285000
0K
0"
0!
b1000 N
1*
#290000
0*
#295000
1K
1$
b1001 N
1*
#300000
0*
#305000
0$
1"
1!
b1010 N
1*
#310000
0*
#315000
0"
0!
0K
b1011 N
1*
#320000
0*
#325000
1K
1$
b1100 N
1*
#330000
0*
#335000
1"
1!
0$
b1101 N
1*
#340000
0*
#345000
0K
0"
0!
b1110 N
1*
#350000
0*
#355000
1K
1$
b1111 N
1*
#360000
0*
#365000
0$
1"
1!
b10000 N
1*
#370000
0*
#375000
0"
0!
0K
b10001 N
1*
#380000
0*
#385000
1K
1$
b10010 N
1*
#390000
0*
#395000
1"
1!
0$
b10011 N
1*
#400000
0*
#405000
0K
0"
0!
b10100 N
1*
#410000
0*
#415000
1K
1$
b10101 N
1*
#420000
0*
#425000
0$
1"
1!
b10110 N
1*
#430000
0*
#435000
0"
0!
0K
b10111 N
1*
#440000
0*
#445000
1K
1$
b11000 N
1*
#450000
0*
#455000
1"
1!
0$
b11001 N
1*
#460000
0*
#465000
0K
0"
0!
b11010 N
1*
#470000
0*
#475000
1K
1$
b11011 N
1*
#480000
0*
#485000
0$
1"
1!
b11100 N
1*
#490000
0*
#495000
0"
0!
0K
b11101 N
1*
#500000
0*
#505000
1K
1$
b11110 N
1*
#510000
0*
#515000
1"
1!
0$
b11111 N
1*
#520000
0*
#525000
0K
0"
0!
b100000 N
1*
#530000
0*
#535000
1K
1$
b100001 N
1*
#540000
0*
#545000
0$
1"
1!
b100010 N
1*
#550000
0*
#555000
0"
0!
0K
b100011 N
1*
#560000
0*
#565000
1K
1$
b100100 N
1*
#570000
0*
#575000
1"
1!
0$
b100101 N
1*
#580000
0*
#585000
0K
0"
0!
b100110 N
1*
#590000
0*
#595000
1K
1$
b100111 N
1*
#600000
0*
#605000
0$
1"
1!
b101000 N
1*
#610000
0*
#615000
0"
0!
0K
b101001 N
1*
#620000
0*
#625000
1K
1$
b101010 N
1*
#630000
0*
#635000
1"
1!
0$
b101011 N
1*
#640000
0*
#645000
0K
0"
0!
b101100 N
1*
#650000
0*
#655000
1K
1$
b101101 N
1*
#660000
0*
#665000
0$
1"
1!
b101110 N
1*
#670000
0*
#675000
0"
0!
0K
b101111 N
1*
#680000
0*
#685000
1K
1$
b110000 N
1*
#690000
0*
#695000
1"
1!
0$
b110001 N
1*
#700000
0*
#705000
0K
0"
0!
b110010 N
1*
#710000
0*
#715000
1K
1$
b110011 N
1*
#720000
0*
#725000
0$
1"
1!
b110100 N
1*
#730000
0*
#735000
0"
0!
0K
b110101 N
1*
#740000
0*
#745000
1K
1$
b110110 N
1*
#750000
0*
#755000
1"
1!
0$
b110111 N
1*
#760000
0*
#765000
0K
0"
0!
b111000 N
1*
#770000
0*
#775000
1K
1$
b111001 N
1*
#780000
0*
#785000
0$
1"
1!
b111010 N
1*
#790000
0*
#795000
0"
0!
0K
b111011 N
1*
#800000
0*
#805000
1K
1$
b111100 N
1*
#810000
0*
#815000
1"
1!
0$
b111101 N
1*
#820000
0*
#825000
0K
0"
0!
b111110 N
1*
#830000
0*
#835000
1K
1$
b111111 N
1*
#840000
0*
#845000
0$
1"
1!
b1000000 N
1*
#850000
0*
#855000
0"
0!
0K
b1000001 N
1*
#860000
0*
#865000
1K
1$
b1000010 N
1*
#870000
0*
#875000
1"
1!
0$
b1000011 N
1*
#880000
0*
#885000
0K
0"
0!
b1000100 N
1*
#890000
0*
#895000
1K
1$
b1000101 N
1*
#900000
0*
#905000
0$
1"
1!
b1000110 N
1*
#910000
0*
#915000
0"
0!
0K
b1000111 N
1*
#920000
0*
#925000
1K
1$
b1001000 N
1*
#930000
0*
#935000
1"
1!
0$
b1001001 N
1*
#940000
0*
#945000
0K
0"
0!
b1001010 N
1*
#950000
0*
#955000
1K
1$
b1001011 N
1*
#960000
0*
#965000
0$
1"
1!
b1001100 N
1*
#970000
0*
#975000
0"
0!
0K
b1001101 N
1*
#980000
0*
#985000
1K
1$
b1001110 N
1*
#990000
0*
#995000
1"
1!
0$
b1001111 N
1*
